lwsspy.ml-0.0.2-py3.9-nspkg.pth
lwsspy/ml/__init__.py
lwsspy/ml/labeling/__init__.py
lwsspy/ml/labeling/segmentlabeler.py
lwsspy/ml/labeling/volumelabeler.py
lwsspy.ml-0.0.2.dist-info/LICENSE
lwsspy.ml-0.0.2.dist-info/METADATA
lwsspy.ml-0.0.2.dist-info/WHEEL
lwsspy.ml-0.0.2.dist-info/namespace_packages.txt
lwsspy.ml-0.0.2.dist-info/top_level.txt
lwsspy.ml-0.0.2.dist-info/RECORD
