Metadata-Version: 2.1
Name: lwsspy.ml
Version: 0.0.2
Summary: Library for Machine Learning Tools.
Home-page: https://github.com/lsawade/lwsspy.ml
Author: Lucas Sawade
Author-email: lsawade@princeton.edu
Maintainer-email: lsawade@princeton.edu
License: UNKNOWN
Project-URL: Documentation, https://lsawade.github.io/lwsspy.ml
Project-URL: TravisCI, https://travis-ci.com/github/lwsspy.ml/
Keywords: Fun,Education,Machine,Learning,Programming
Platform: UNKNOWN
Classifier: Programming Language :: Python :: 3
Classifier: License :: OSI Approved :: GNU General Public License v3 or later (GPLv3+)
Classifier: Operating System :: OS Independent
Requires-Python: >=3.6
License-File: LICENSE
Requires-Dist: numpy
Requires-Dist: matplotlib
Requires-Dist: scikit-image
Provides-Extra: docs
Requires-Dist: sphinx ; extra == 'docs'
Requires-Dist: numpydoc ; extra == 'docs'
Requires-Dist: sphinx-book-theme ; extra == 'docs'
Provides-Extra: tests
Requires-Dist: pytest ; extra == 'tests'
